carsharefile/ShareFile_errors.py
carsharefile/ShareFile_master.py
carsharefile/__init__.py
carsharefile-0.4.dist-info/LICENSE.txt
carsharefile-0.4.dist-info/METADATA
carsharefile-0.4.dist-info/WHEEL
carsharefile-0.4.dist-info/top_level.txt
carsharefile-0.4.dist-info/RECORD
