Metadata-Version: 2.1
Name: carsharefile
Version: 0.4
Summary: Python Package that provides easy interaction with the ShareFile API.
Home-page: UNKNOWN
Author: Sam Rubanowitz
Author-email: therealsamurban@gmail.com
License: MIT
Platform: UNKNOWN
